MANIFEST.in
README
VERSION
setup.cfg
setup.py
repoze/__init__.py
repoze.who_x509.egg-info/PKG-INFO
repoze.who_x509.egg-info/SOURCES.txt
repoze.who_x509.egg-info/dependency_links.txt
repoze.who_x509.egg-info/namespace_packages.txt
repoze.who_x509.egg-info/requires.txt
repoze.who_x509.egg-info/top_level.txt
repoze.who_x509.egg-info/zip-safe
repoze/who/__init__.py
repoze/who/plugins/__init__.py
repoze/who/plugins/x509/__init__.py
repoze/who/plugins/x509/utils.py