Metadata-Version: 1.0
Name: repoze.who-x509
Version: 0.2.0
Summary: x509 repoze.who plugin
Home-page: http://www.ckluster.com/
Author: Arturo Sevilla
Author-email: arturo@ckluster.com
License: Modified BSD License (http://www.ckluster.com/OPEN_LICENSE.txt)
Keywords: web x509 repoze who authentication client certificate
Platform: UNKNOWN
Classifier: Development Status :: 4 - Beta
Classifier: Environment :: Web Environment
Classifier: License :: OSI Approved :: BSD License
Classifier: Intended Audience :: Developers
Classifier: Natural Language :: English
Classifier: Operating System :: OS Independent
Classifier: Programming Language :: Python
Classifier: Topic :: Security
